{"newsList1":{"nTitle":"2023년 중소기업 스마트제조혁신사업 지원안내","nDate":"2023-01-13","nLink":"https://www.koita.or.kr/notice/notice_view.aspx?no=4772"},"newsList2":{"nTitle":"2023년 상반기 중소·벤처 기업부설연구소 선정 신청 공고","nDate":"2023-01-16","nLink":"https://www.koita.or.kr/notice/notice_view.aspx?no=4774"},"newsList3":{"nTitle":"기업부설연구소/연구개발전담부서 취소 전 청문 안내 및 인정취소...","nDate":"2023-01-18","nLink":"https://www.koita.or.kr/notice/notice_view.aspx?no=4775"},"newsList4":{"nTitle":"기업부설연구소/연구개발전담부서 취소 전 청문 안내 및 인정취소...","nDate":"2023-01-18","nLink":"https://www.koita.or.kr/notice/notice_view.aspx?no=4776"},"newsList5":{"nTitle":"제101차 IR52 장영실상(`23년 18주~34주) 신청안내","nDate":"2022-12-19","nLink":"https://www.koita.or.kr/notice/notice_view.aspx?no=4760"},"newsList6":{"nTitle":"디지털 전환(DT) 협의체 참가 안내","nDate":"2023-01-03","nLink":"https://www.koita.or.kr/notice/notice_view.aspx?no=4765"},"newsList7":{"nTitle":"2023년도 제1회 이사회 개최 안내","nDate":"2023-01-05","nLink":"https://www.koita.or.kr/notice/notice_view.aspx?no=4768"},"newsList8":{"nTitle":"산기협 제45차 정기총회 개최 안내","nDate":"2023-01-05","nLink":"https://www.koita.or.kr/notice/notice_view.aspx?no=4769"},"newsList9":{"nTitle":"2023년 이공계 전문기술 연수사업 공고","nDate":"2023-01-09","nLink":"https://www.koita.or.kr/notice/notice_view.aspx?no=4770"},"newsList10":{"nTitle":"제69차 대한민국 엔지니어상 선정계획 공고","nDate":"2023-01-16","nLink":"https://www.koita.or.kr/notice/notice_view.aspx?no=4773"}}