{"newsList1":{"nTitle":"철골 구조물에서 작업 중 떨어짐","nDate":"2022/10","nLink":"https://www.kosha.or.kr/kosha/report/kosha_news.do?mode=view&articleNo=436086&article.offset=0&articleLimit=10"},"newsList2":{"nTitle":"굴착매설 작업 중 토사붕괴","nDate":"2022/11","nLink":"https://www.kosha.or.kr/kosha/report/kosha_news.do?mode=view&articleNo=436847&article.offset=0&articleLimit=10"},"newsList3":{"nTitle":"지붕 보수공사 중 재광창이 파손되어 추락","nDate":"2022/11","nLink":"https://www.kosha.or.kr/kosha/report/kosha_news.do?mode=view&articleNo=436848&article.offset=0&articleLimit=10"},"newsList4":{"nTitle":"해체 중인 사보강재가 떨어져 근로자 맞음","nDate":"2022/11","nLink":"https://www.kosha.or.kr/kosha/report/kosha_news.do?mode=view&articleNo=436849&article.offset=0&articleLimit=10"},"newsList5":{"nTitle":"개구부 아래로 떨어짐","nDate":"2022/12","nLink":"https://www.kosha.or.kr/kosha/report/kosha_news.do?mode=view&articleNo=437541&article.offset=0&articleLimit=10"},"newsList6":{"nTitle":"처마 위에서 청소작업 중 떨어짐","nDate":"2022/12","nLink":"https://www.kosha.or.kr/kosha/report/kosha_news.do?mode=view&articleNo=437542&article.offset=0&articleLimit=10"},"newsList7":{"nTitle":"파단된 이동식크레인 붐에 맞음","nDate":"2022/12","nLink":"https://www.kosha.or.kr/kosha/report/kosha_news.do?mode=view&articleNo=437543&article.offset=0&articleLimit=10"},"newsList8":{"nTitle":"SWC 작업발판에서 떨어짐","nDate":"2023/01","nLink":"https://www.kosha.or.kr/kosha/report/kosha_news.do?mode=view&articleNo=437784&article.offset=0&articleLimit=10"},"newsList9":{"nTitle":"수상 작업발판 이동 중 익사","nDate":"2023/01","nLink":"https://www.kosha.or.kr/kosha/report/kosha_news.do?mode=view&articleNo=437785&article.offset=0&articleLimit=10"},"newsList10":{"nTitle":"콘크리트 타설 중 거푸집동바리 붕괴","nDate":"2023/01","nLink":"https://www.kosha.or.kr/kosha/report/kosha_news.do?mode=view&articleNo=437786&article.offset=0&articleLimit=10"}}